AutoStrEnum/__init__.py
AutoStrEnum/auto_string_enum.py
AutoStrEnum-0.0.10.dist-info/LICENSE
AutoStrEnum-0.0.10.dist-info/METADATA
AutoStrEnum-0.0.10.dist-info/WHEEL
AutoStrEnum-0.0.10.dist-info/top_level.txt
AutoStrEnum-0.0.10.dist-info/RECORD
