Metadata-Version: 2.1
Name: AutoStrEnum
Version: 0.0.10
Summary: # AutoStrEnum
Home-page: https://github.com/PttCodingMan/AutoStrEnum
Author: CodingMan
Author-email: pttcodingman@gmail.com
License: UNKNOWN
Keywords: enum
Platform: UNKNOWN
Classifier: Development Status :: 5 - Production/Stable
Classifier: Operating System :: OS Independent
Classifier: Topic :: Software Development :: Libraries :: Python Modules
Classifier: License :: OSI Approved :: MIT License
Classifier: Programming Language :: Python :: 3.8
Classifier: Programming Language :: Python :: 3.9
Classifier: Programming Language :: Python :: 3.10
Requires-Python: >=3.8
License-File: LICENSE
